pyserialgps/__init__.py
pyserialgps/gpsmodule.py
pyserialgps/manager.py
pyserialgps-0.0.1.dist-info/METADATA
pyserialgps-0.0.1.dist-info/WHEEL
pyserialgps-0.0.1.dist-info/licenses/LICENSE.md
pyserialgps-0.0.1.dist-info/RECORD
