Metadata-Version: 2.4
Name: pyserialgps
Version: 0.0.1
Summary: Interact with serial GPS modules.
Project-URL: Homepage, https://github.com/antoniovazquezblanco/pyserialgps
Project-URL: Bug Tracker, https://github.com/antoniovazquezblanco/pyserialgps/issues
Author-email: Antonio Vázquez Blanco <antoniovazquezblanco@gmail.com>
License: GPL-3.0-only
License-File: LICENSE.md
Keywords: GPS,geolocation,serial
Classifier: Intended Audience :: Developers
Classifier: License :: OSI Approved :: GNU General Public License v3 (GPLv3)
Classifier: Operating System :: OS Independent
Classifier: Programming Language :: Python :: 3
Requires-Python: >=3.0
Requires-Dist: pynmea2
Requires-Dist: pyserial
